tdxpy/__init__.py
tdxpy/base_socket_client.py
tdxpy/constants.py
tdxpy/crawler/__init__.py
tdxpy/crawler/base_crawler.py
tdxpy/crawler/history_financial_crawler.py
tdxpy/exceptions.py
tdxpy/exhq.py
tdxpy/heartbeat.py
tdxpy/helper.py
tdxpy/hq.py
tdxpy/logger.py
tdxpy/parser/__init__.py
tdxpy/parser/base.py
tdxpy/parser/ext/__init__.py
tdxpy/parser/ext/ex_get_history_instrument_bars_range.py
tdxpy/parser/ext/ex_get_history_minute_time_data.py
tdxpy/parser/ext/ex_get_history_transaction_data.py
tdxpy/parser/ext/ex_get_instrument_bars.py
tdxpy/parser/ext/ex_get_instrument_count.py
tdxpy/parser/ext/ex_get_instrument_info.py
tdxpy/parser/ext/ex_get_instrument_quote.py
tdxpy/parser/ext/ex_get_instrument_quote_list.py
tdxpy/parser/ext/ex_get_markets.py
tdxpy/parser/ext/ex_get_minute_time_data.py
tdxpy/parser/ext/ex_get_transaction_data.py
tdxpy/parser/raw_parser.py
tdxpy/parser/setup_commands.py
tdxpy/parser/std/__init__.py
tdxpy/parser/std/get_block_info.py
tdxpy/parser/std/get_company_info_category.py
tdxpy/parser/std/get_company_info_content.py
tdxpy/parser/std/get_finance_info.py
tdxpy/parser/std/get_history_minute_time_data.py
tdxpy/parser/std/get_history_transaction_data.py
tdxpy/parser/std/get_index_bars.py
tdxpy/parser/std/get_minute_time_data.py
tdxpy/parser/std/get_report_file.py
tdxpy/parser/std/get_security_bars.py
tdxpy/parser/std/get_security_count.py
tdxpy/parser/std/get_security_list.py
tdxpy/parser/std/get_security_quotes.py
tdxpy/parser/std/get_transaction_data.py
tdxpy/parser/std/get_xdxr_info.py
tdxpy/reader/__init__.py
tdxpy/reader/base_reader.py
tdxpy/reader/block_reader.py
tdxpy/reader/daily_bar_reader.py
tdxpy/reader/exhq_daily_bar_reader.py
tdxpy/reader/history_financial_reader.py
tdxpy/reader/lc_min_bar_reader.py
tdxpy/reader/min_bar_reader.py
tdxpy/version.py
tdxpy-0.2.6.dist-info/LICENSE
tdxpy-0.2.6.dist-info/METADATA
tdxpy-0.2.6.dist-info/WHEEL
tdxpy-0.2.6.dist-info/RECORD
