Metadata-Version: 2.1
Name: tdxpy
Version: 0.2.6
Summary: 通达信数据读取接口.
Home-page: https://www.mootdx.com/tdxpy
License: MIT
Author: bopo
Author-email: ibopo@126.com
Requires-Python: >=3.8,<4.0
Classifier: Development Status :: 2 - Pre-Alpha
Classifier: Intended Audience :: Developers
Classifier: License :: OSI Approved :: MIT License
Classifier: Natural Language :: English
Classifier: Programming Language :: Python :: 3
Classifier: Programming Language :: Python :: 3.8
Classifier: Programming Language :: Python :: 3.9
Classifier: Programming Language :: Python :: 3.10
Classifier: Programming Language :: Python :: 3.11
Classifier: Programming Language :: Python :: 3.12
Classifier: Programming Language :: Python :: 3.6
Classifier: Programming Language :: Python :: 3.7
Requires-Dist: pandas
Project-URL: Repository, https://github.com/mootdx/tdxpy
